{
  "swagger" : "2.0",
  "info" : {
    "version" : "2024-12-05T10:41:09Z",
    "title" : "RestAPI"
  },
  "host" : "6up6i7wsrb.execute-api.ap-northeast-3.amazonaws.com",
  "basePath" : "/prod",
  "schemes" : [ "https" ],
  "paths" : {
    "/" : {
      "options" : {
        "consumes" : [ "application/json" ],
        "responses" : {
          "204" : {
            "description" : "204 response",
            "headers" : {
              "Access-Control-Allow-Origin" : {
                "type" : "string"
              },
              "Access-Control-Allow-Methods" : {
                "type" : "string"
              },
              "Access-Control-Allow-Headers" : {
                "type" : "string"
              }
            }
          }
        },
        "x-amazon-apigateway-integration" : {
          "responses" : {
            "default" : {
              "statusCode" : "204",
              "responseParameters" : {
                "method.response.header.Access-Control-Allow-Methods" : "'OPTIONS,GET,PUT,POST,DELETE,PATCH,HEAD'",
                "method.response.header.Access-Control-Allow-Headers" : "'Content-Type,X-Amz-Date,Authorization,X-Api-Key,X-Amz-Security-Token,X-Amz-User-Agent'",
                "method.response.header.Access-Control-Allow-Origin" : "'*'"
              }
            }
          },
          "requestTemplates" : {
            "application/json" : "{ statusCode: 200 }"
          },
          "passthroughBehavior" : "when_no_match",
          "type" : "mock"
        }
      }
    },
    "/sensor-data" : {
      "get" : {
        "responses" : { },
        "x-amazon-apigateway-integration" : {
          "httpMethod" : "POST",
          "uri" : "arn:aws:apigateway:ap-northeast-3:lambda:path/2015-03-31/functions/arn:aws:lambda:ap-northeast-3:471112772417:function:IotWebApiStack-SensorLambda2641F1B0-e9pLAAFmrIr1/invocations",
          "passthroughBehavior" : "when_no_match",
          "type" : "aws_proxy"
        }
      },
      "post" : {
        "responses" : { },
        "x-amazon-apigateway-integration" : {
          "httpMethod" : "POST",
          "uri" : "arn:aws:apigateway:ap-northeast-3:lambda:path/2015-03-31/functions/arn:aws:lambda:ap-northeast-3:471112772417:function:IotWebApiStack-SensorLambda2641F1B0-e9pLAAFmrIr1/invocations",
          "passthroughBehavior" : "when_no_match",
          "type" : "aws_proxy"
        }
      },
      "options" : {
        "consumes" : [ "application/json" ],
        "responses" : {
          "204" : {
            "description" : "204 response",
            "headers" : {
              "Access-Control-Allow-Origin" : {
                "type" : "string"
              },
              "Access-Control-Allow-Methods" : {
                "type" : "string"
              },
              "Access-Control-Allow-Headers" : {
                "type" : "string"
              }
            }
          }
        },
        "x-amazon-apigateway-integration" : {
          "responses" : {
            "default" : {
              "statusCode" : "204",
              "responseParameters" : {
                "method.response.header.Access-Control-Allow-Methods" : "'OPTIONS,GET,PUT,POST,DELETE,PATCH,HEAD'",
                "method.response.header.Access-Control-Allow-Headers" : "'Content-Type,X-Amz-Date,Authorization,X-Api-Key,X-Amz-Security-Token,X-Amz-User-Agent'",
                "method.response.header.Access-Control-Allow-Origin" : "'*'"
              }
            }
          },
          "requestTemplates" : {
            "application/json" : "{ statusCode: 200 }"
          },
          "passthroughBehavior" : "when_no_match",
          "type" : "mock"
        }
      }
    },
    "/sensor-data/{id}" : {
      "get" : {
        "parameters" : [ {
          "name" : "id",
          "in" : "path",
          "required" : true,
          "type" : "string"
        } ],
        "responses" : { },
        "x-amazon-apigateway-integration" : {
          "httpMethod" : "POST",
          "uri" : "arn:aws:apigateway:ap-northeast-3:lambda:path/2015-03-31/functions/arn:aws:lambda:ap-northeast-3:471112772417:function:IotWebApiStack-SensorLambda2641F1B0-e9pLAAFmrIr1/invocations",
          "passthroughBehavior" : "when_no_match",
          "type" : "aws_proxy"
        }
      },
      "put" : {
        "parameters" : [ {
          "name" : "id",
          "in" : "path",
          "required" : true,
          "type" : "string"
        } ],
        "responses" : { },
        "x-amazon-apigateway-integration" : {
          "httpMethod" : "POST",
          "uri" : "arn:aws:apigateway:ap-northeast-3:lambda:path/2015-03-31/functions/arn:aws:lambda:ap-northeast-3:471112772417:function:IotWebApiStack-SensorLambda2641F1B0-e9pLAAFmrIr1/invocations",
          "passthroughBehavior" : "when_no_match",
          "type" : "aws_proxy"
        }
      },
      "delete" : {
        "parameters" : [ {
          "name" : "id",
          "in" : "path",
          "required" : true,
          "type" : "string"
        } ],
        "responses" : { },
        "x-amazon-apigateway-integration" : {
          "httpMethod" : "POST",
          "uri" : "arn:aws:apigateway:ap-northeast-3:lambda:path/2015-03-31/functions/arn:aws:lambda:ap-northeast-3:471112772417:function:IotWebApiStack-SensorLambda2641F1B0-e9pLAAFmrIr1/invocations",
          "passthroughBehavior" : "when_no_match",
          "type" : "aws_proxy"
        }
      },
      "options" : {
        "consumes" : [ "application/json" ],
        "parameters" : [ {
          "name" : "id",
          "in" : "path",
          "required" : true,
          "type" : "string"
        } ],
        "responses" : {
          "204" : {
            "description" : "204 response",
            "headers" : {
              "Access-Control-Allow-Origin" : {
                "type" : "string"
              },
              "Access-Control-Allow-Methods" : {
                "type" : "string"
              },
              "Access-Control-Allow-Headers" : {
                "type" : "string"
              }
            }
          }
        },
        "x-amazon-apigateway-integration" : {
          "responses" : {
            "default" : {
              "statusCode" : "204",
              "responseParameters" : {
                "method.response.header.Access-Control-Allow-Methods" : "'OPTIONS,GET,PUT,POST,DELETE,PATCH,HEAD'",
                "method.response.header.Access-Control-Allow-Headers" : "'Content-Type,X-Amz-Date,Authorization,X-Api-Key,X-Amz-Security-Token,X-Amz-User-Agent'",
                "method.response.header.Access-Control-Allow-Origin" : "'*'"
              }
            }
          },
          "requestTemplates" : {
            "application/json" : "{ statusCode: 200 }"
          },
          "passthroughBehavior" : "when_no_match",
          "type" : "mock"
        }
      }
    },
    "/user" : {
      "get" : {
        "responses" : { },
        "x-amazon-apigateway-integration" : {
          "httpMethod" : "POST",
          "uri" : "arn:aws:apigateway:ap-northeast-3:lambda:path/2015-03-31/functions/arn:aws:lambda:ap-northeast-3:471112772417:function:IotWebApiStack-UserLambdaAD4FB23B-EEabvdyP4f09/invocations",
          "passthroughBehavior" : "when_no_match",
          "type" : "aws_proxy"
        }
      },
      "options" : {
        "consumes" : [ "application/json" ],
        "responses" : {
          "204" : {
            "description" : "204 response",
            "headers" : {
              "Access-Control-Allow-Origin" : {
                "type" : "string"
              },
              "Access-Control-Allow-Methods" : {
                "type" : "string"
              },
              "Access-Control-Allow-Headers" : {
                "type" : "string"
              }
            }
          }
        },
        "x-amazon-apigateway-integration" : {
          "responses" : {
            "default" : {
              "statusCode" : "204",
              "responseParameters" : {
                "method.response.header.Access-Control-Allow-Methods" : "'OPTIONS,GET,PUT,POST,DELETE,PATCH,HEAD'",
                "method.response.header.Access-Control-Allow-Headers" : "'Content-Type,X-Amz-Date,Authorization,X-Api-Key,X-Amz-Security-Token,X-Amz-User-Agent'",
                "method.response.header.Access-Control-Allow-Origin" : "'*'"
              }
            }
          },
          "requestTemplates" : {
            "application/json" : "{ statusCode: 200 }"
          },
          "passthroughBehavior" : "when_no_match",
          "type" : "mock"
        }
      }
    },
    "/user/{id}" : {
      "get" : {
        "parameters" : [ {
          "name" : "id",
          "in" : "path",
          "required" : true,
          "type" : "string"
        } ],
        "responses" : { },
        "x-amazon-apigateway-integration" : {
          "httpMethod" : "POST",
          "uri" : "arn:aws:apigateway:ap-northeast-3:lambda:path/2015-03-31/functions/arn:aws:lambda:ap-northeast-3:471112772417:function:IotWebApiStack-UserLambdaAD4FB23B-EEabvdyP4f09/invocations",
          "passthroughBehavior" : "when_no_match",
          "type" : "aws_proxy"
        }
      },
      "post" : {
        "parameters" : [ {
          "name" : "id",
          "in" : "path",
          "required" : true,
          "type" : "string"
        } ],
        "responses" : { },
        "x-amazon-apigateway-integration" : {
          "httpMethod" : "POST",
          "uri" : "arn:aws:apigateway:ap-northeast-3:lambda:path/2015-03-31/functions/arn:aws:lambda:ap-northeast-3:471112772417:function:IotWebApiStack-UserLambdaAD4FB23B-EEabvdyP4f09/invocations",
          "passthroughBehavior" : "when_no_match",
          "type" : "aws_proxy"
        }
      },
      "options" : {
        "consumes" : [ "application/json" ],
        "parameters" : [ {
          "name" : "id",
          "in" : "path",
          "required" : true,
          "type" : "string"
        } ],
        "responses" : {
          "204" : {
            "description" : "204 response",
            "headers" : {
              "Access-Control-Allow-Origin" : {
                "type" : "string"
              },
              "Access-Control-Allow-Methods" : {
                "type" : "string"
              },
              "Access-Control-Allow-Headers" : {
                "type" : "string"
              }
            }
          }
        },
        "x-amazon-apigateway-integration" : {
          "responses" : {
            "default" : {
              "statusCode" : "204",
              "responseParameters" : {
                "method.response.header.Access-Control-Allow-Methods" : "'OPTIONS,GET,PUT,POST,DELETE,PATCH,HEAD'",
                "method.response.header.Access-Control-Allow-Headers" : "'Content-Type,X-Amz-Date,Authorization,X-Api-Key,X-Amz-Security-Token,X-Amz-User-Agent'",
                "method.response.header.Access-Control-Allow-Origin" : "'*'"
              }
            }
          },
          "requestTemplates" : {
            "application/json" : "{ statusCode: 200 }"
          },
          "passthroughBehavior" : "when_no_match",
          "type" : "mock"
        }
      }
    },
    "/users" : {
      "get" : {
        "responses" : { },
        "x-amazon-apigateway-integration" : {
          "httpMethod" : "POST",
          "uri" : "arn:aws:apigateway:ap-northeast-3:lambda:path/2015-03-31/functions/arn:aws:lambda:ap-northeast-3:471112772417:function:IotWebApiStack-UserLambdaAD4FB23B-EEabvdyP4f09/invocations",
          "passthroughBehavior" : "when_no_match",
          "type" : "aws_proxy"
        }
      },
      "post" : {
        "responses" : { },
        "x-amazon-apigateway-integration" : {
          "httpMethod" : "POST",
          "uri" : "arn:aws:apigateway:ap-northeast-3:lambda:path/2015-03-31/functions/arn:aws:lambda:ap-northeast-3:471112772417:function:IotWebApiStack-UserLambdaAD4FB23B-EEabvdyP4f09/invocations",
          "passthroughBehavior" : "when_no_match",
          "type" : "aws_proxy"
        }
      },
      "options" : {
        "consumes" : [ "application/json" ],
        "responses" : {
          "204" : {
            "description" : "204 response",
            "headers" : {
              "Access-Control-Allow-Origin" : {
                "type" : "string"
              },
              "Access-Control-Allow-Methods" : {
                "type" : "string"
              },
              "Access-Control-Allow-Headers" : {
                "type" : "string"
              }
            }
          }
        },
        "x-amazon-apigateway-integration" : {
          "responses" : {
            "default" : {
              "statusCode" : "204",
              "responseParameters" : {
                "method.response.header.Access-Control-Allow-Methods" : "'OPTIONS,GET,PUT,POST,DELETE,PATCH,HEAD'",
                "method.response.header.Access-Control-Allow-Headers" : "'Content-Type,X-Amz-Date,Authorization,X-Api-Key,X-Amz-Security-Token,X-Amz-User-Agent'",
                "method.response.header.Access-Control-Allow-Origin" : "'*'"
              }
            }
          },
          "requestTemplates" : {
            "application/json" : "{ statusCode: 200 }"
          },
          "passthroughBehavior" : "when_no_match",
          "type" : "mock"
        }
      }
    },
    "/users/{id}" : {
      "get" : {
        "parameters" : [ {
          "name" : "id",
          "in" : "path",
          "required" : true,
          "type" : "string"
        } ],
        "responses" : { },
        "x-amazon-apigateway-integration" : {
          "httpMethod" : "POST",
          "uri" : "arn:aws:apigateway:ap-northeast-3:lambda:path/2015-03-31/functions/arn:aws:lambda:ap-northeast-3:471112772417:function:IotWebApiStack-UserLambdaAD4FB23B-EEabvdyP4f09/invocations",
          "passthroughBehavior" : "when_no_match",
          "type" : "aws_proxy"
        }
      },
      "put" : {
        "parameters" : [ {
          "name" : "id",
          "in" : "path",
          "required" : true,
          "type" : "string"
        } ],
        "responses" : { },
        "x-amazon-apigateway-integration" : {
          "httpMethod" : "POST",
          "uri" : "arn:aws:apigateway:ap-northeast-3:lambda:path/2015-03-31/functions/arn:aws:lambda:ap-northeast-3:471112772417:function:IotWebApiStack-UserLambdaAD4FB23B-EEabvdyP4f09/invocations",
          "passthroughBehavior" : "when_no_match",
          "type" : "aws_proxy"
        }
      },
      "delete" : {
        "parameters" : [ {
          "name" : "id",
          "in" : "path",
          "required" : true,
          "type" : "string"
        } ],
        "responses" : { },
        "x-amazon-apigateway-integration" : {
          "httpMethod" : "POST",
          "uri" : "arn:aws:apigateway:ap-northeast-3:lambda:path/2015-03-31/functions/arn:aws:lambda:ap-northeast-3:471112772417:function:IotWebApiStack-UserLambdaAD4FB23B-EEabvdyP4f09/invocations",
          "passthroughBehavior" : "when_no_match",
          "type" : "aws_proxy"
        }
      },
      "options" : {
        "consumes" : [ "application/json" ],
        "parameters" : [ {
          "name" : "id",
          "in" : "path",
          "required" : true,
          "type" : "string"
        } ],
        "responses" : {
          "204" : {
            "description" : "204 response",
            "headers" : {
              "Access-Control-Allow-Origin" : {
                "type" : "string"
              },
              "Access-Control-Allow-Methods" : {
                "type" : "string"
              },
              "Access-Control-Allow-Headers" : {
                "type" : "string"
              }
            }
          }
        },
        "x-amazon-apigateway-integration" : {
          "responses" : {
            "default" : {
              "statusCode" : "204",
              "responseParameters" : {
                "method.response.header.Access-Control-Allow-Methods" : "'OPTIONS,GET,PUT,POST,DELETE,PATCH,HEAD'",
                "method.response.header.Access-Control-Allow-Headers" : "'Content-Type,X-Amz-Date,Authorization,X-Api-Key,X-Amz-Security-Token,X-Amz-User-Agent'",
                "method.response.header.Access-Control-Allow-Origin" : "'*'"
              }
            }
          },
          "requestTemplates" : {
            "application/json" : "{ statusCode: 200 }"
          },
          "passthroughBehavior" : "when_no_match",
          "type" : "mock"
        }
      }
    }
  }
}